person_counter/__init__.py
person_counter/model.py
person_counter/trackers/__init__.py
person_counter/trackers/multi_tracker_zoo.py
person_counter/trackers/bytetrack/__init__.py
person_counter/trackers/bytetrack/basetrack.py
person_counter/trackers/bytetrack/byte_tracker.py
person_counter/trackers/bytetrack/kalman_filter.py
person_counter/trackers/bytetrack/matching.py
person_counter/trackers/ocsort/__init__.py
person_counter/trackers/ocsort/association.py
person_counter/trackers/ocsort/kalmanfilter.py
person_counter/trackers/ocsort/ocsort.py
person_counter/trackers/strong_sort/__init__.py
person_counter/trackers/strong_sort/reid_multibackend.py
person_counter/trackers/strong_sort/strong_sort.py
person_counter/trackers/strong_sort/deep/__init__.py
person_counter/trackers/strong_sort/deep/reid_model_factory.py
person_counter/trackers/strong_sort/deep/models/__init__.py
person_counter/trackers/strong_sort/deep/models/densenet.py
person_counter/trackers/strong_sort/deep/models/hacnn.py
person_counter/trackers/strong_sort/deep/models/inceptionresnetv2.py
person_counter/trackers/strong_sort/deep/models/inceptionv4.py
person_counter/trackers/strong_sort/deep/models/mlfn.py
person_counter/trackers/strong_sort/deep/models/mobilenetv2.py
person_counter/trackers/strong_sort/deep/models/mudeep.py
person_counter/trackers/strong_sort/deep/models/nasnet.py
person_counter/trackers/strong_sort/deep/models/osnet.py
person_counter/trackers/strong_sort/deep/models/osnet_ain.py
person_counter/trackers/strong_sort/deep/models/pcb.py
person_counter/trackers/strong_sort/deep/models/resnet.py
person_counter/trackers/strong_sort/deep/models/resnet_ibn_a.py
person_counter/trackers/strong_sort/deep/models/resnet_ibn_b.py
person_counter/trackers/strong_sort/deep/models/resnetmid.py
person_counter/trackers/strong_sort/deep/models/senet.py
person_counter/trackers/strong_sort/deep/models/shufflenet.py
person_counter/trackers/strong_sort/deep/models/shufflenetv2.py
person_counter-1.1.30.dist-info/LICENSE
person_counter-1.1.30.dist-info/METADATA
person_counter-1.1.30.dist-info/WHEEL
person_counter-1.1.30.dist-info/top_level.txt
person_counter-1.1.30.dist-info/RECORD
