Metadata-Version: 2.1
Name: person-counter
Version: 1.1.30
Summary: Person Counter using torch
Author: Olivier
Author-email: luowensheng2018@gmail.com
Keywords: python,person,counting,AI
Classifier: Development Status :: 1 - Planning
Classifier: Intended Audience :: Developers
Classifier: Programming Language :: Python :: 3
Classifier: Operating System :: Unix
Classifier: Operating System :: MacOS :: MacOS X
Classifier: Operating System :: Microsoft :: Windows
License-File: LICENSE
Requires-Dist: Cython
Requires-Dist: opencv-stream
Requires-Dist: torch
Requires-Dist: torchvision
Requires-Dist: tensorflow
Requires-Dist: filterpy
Requires-Dist: lap
Requires-Dist: gdown
Requires-Dist: Pillow (>=7.1.2)
Requires-Dist: PyYAML (>=5.3.1)
Requires-Dist: six
Requires-Dist: pandas
Requires-Dist: easydict
